pied_poker/__init__.py
pied_poker/card/__init__.py
pied_poker/card/card.py
pied_poker/card/comparable.py
pied_poker/card/rank.py
pied_poker/card/suit.py
pied_poker/deck/__init__.py
pied_poker/deck/deck.py
pied_poker/hand/__init__.py
pied_poker/hand/base_hand.py
pied_poker/hand/empty_hand.py
pied_poker/hand/flush.py
pied_poker/hand/four_of_a_kind.py
pied_poker/hand/full_house.py
pied_poker/hand/high_card.py
pied_poker/hand/killer_card.py
pied_poker/hand/one_pair.py
pied_poker/hand/out.py
pied_poker/hand/poker_hand.py
pied_poker/hand/poker_hand_result.py
pied_poker/hand/royal_flush.py
pied_poker/hand/straight.py
pied_poker/hand/straight_flush.py
pied_poker/hand/three_of_a_kind.py
pied_poker/hand/two_pair.py
pied_poker/player/__init__.py
pied_poker/player/player.py
pied_poker/poker_round/__init__.py
pied_poker/poker_round/poker_round.py
pied_poker/poker_round/poker_round_result.py
pied_poker/poker_round/poker_round_simulation_result.py
pied_poker/poker_round/poker_round_simulator.py
pied_poker/poker_round/round_result.py
pied_poker/poker_round/round_simulator.py
pied_poker/probability/__init__.py
pied_poker/probability/base_poker_event.py
pied_poker/probability/probability_value.py
pied_poker/probability/simulation_probability.py
pied_poker/probability/events/__init__.py
pied_poker/probability/events/community_cards_include.py
pied_poker/probability/events/no_tie.py
pied_poker/probability/events/player_has_card_ranks.py
pied_poker/probability/events/player_has_card_suits.py
pied_poker/probability/events/player_has_cards.py
pied_poker/probability/events/player_has_hand.py
pied_poker/probability/events/player_has_hand_or_higher.py
pied_poker/probability/events/player_has_pocket_pair.py
pied_poker/probability/events/player_has_suited_cards.py
pied_poker/probability/events/player_loses.py
pied_poker/probability/events/player_wins.py
pied_poker/probability/events/player_wins_with_tie.py
pied_poker/probability/events/tie.py
pied_poker/visualization/__init__.py
pied_poker-1.3.6.dist-info/METADATA
pied_poker-1.3.6.dist-info/WHEEL
pied_poker-1.3.6.dist-info/top_level.txt
pied_poker-1.3.6.dist-info/RECORD
