Metadata-Version: 2.1
Name: pied-poker
Version: 1.3.6
Summary: A Python package to run flexible and fast poker simulations using a monte carlo style simulator.
Home-page: https://github.com/elleklinton/PiedPoker
Author: Ellek Linton
Author-email: ellek@elleklinton.com
License: GNU LGPLv3
Platform: UNKNOWN
Classifier: Development Status :: 1 - Planning
Classifier: Intended Audience :: Developers
Classifier: License :: Free for non-commercial use
Classifier: Topic :: Games/Entertainment :: Simulation
Classifier: Topic :: Games/Entertainment
Classifier: Programming Language :: Python :: 3.8
Classifier: Development Status :: 4 - Beta
Requires-Dist: joblib
Requires-Dist: tqdm
Requires-Dist: numpy
Requires-Dist: seaborn
Requires-Dist: pandas
Requires-Dist: matplotlib
Requires-Dist: scipy
